FWU/FWLU.py
FWU/FWLU1D.py
FWU/FWLU1DT.py
FWU/FWLU2D.py
FWU/FWLU2DT.py
FWU/FWMU.py
FWU/FWMU1D.py
FWU/FWMU1DT.py
FWU/FWMU2D.py
FWU/FWMU2DT.py
FWU/__init__.py
FWU/transOrthogonal_.py
fwu-0.0.4.dist-info/licenses/LICENSE
fwu-0.0.4.dist-info/METADATA
fwu-0.0.4.dist-info/WHEEL
fwu-0.0.4.dist-info/top_level.txt
fwu-0.0.4.dist-info/RECORD
