Metadata-Version: 2.4
Name: FWU
Version: 0.0.4
Summary: FWU is a series of PyTorch-based neural network units. It has higher information utilization, prevents neuronal necrosis, and eliminates the need to add additionall activation functions. 
Author-email: Psyche Halo <Psyche@WinsGod.com>
Project-URL: Homepage, https://github.com/PsycheHalo/FWU
Project-URL: Issues, https://github.com/PsycheHalo/FWU/issues
Keywords: FWU,FWLU,FWMU,PyTorch,AI,neural,NN,unit
Classifier: Programming Language :: Python :: 3
Classifier: Operating System :: OS Independent
Requires-Python: >=3.8
License-File: LICENSE
Requires-Dist: torch>=1.7.0
Dynamic: license-file
